{
  "n lote": 56,
  "IDequipo": "C67",
  "fecha": "2024-07-22",
  "hora": "00:55:06",
  "elapsedtime": "28.000",
  "unidades": [
    "-",
    "-",
    "-",
    "Elapsed time = s",
    "ECG = mV",
    "PPG = a.u.",
    "Resp = L/min",
    "Spo2 = %",
    "temp = \u00b0C",
    "SIS = mmHg",
    "DIA = mmHg"
  ],
  "frecuencia": [
    "-",
    "-",
    "-",
    "-",
    "ECG = 1000 Hz",
    "PPG = 100 Hz",
    "Resp = 100 Hz",
    "spo2 = 100 Hz",
    "temp = 100 Hz",
    "SIS = 100 Hz",
    "DIA = 100 Hz"
  ],
  "ECG": [
    0.08,
    0.077,
    0.074,
    0.071,
    0.067,
    0.064,
    0.061,
    0.058,
    0.055,
    0.053,
    0.05,
    0.047,
    0.045,
    0.043,
    0.041,
    0.038,
    0.036,
    0.034,
    0.032,
    0.029,
    0.027,
    0.024,
    0.021,
    0.018,
    0.014,
    0.01,
    0.006,
    0.001,
    -0.004,
    -0.01,
    -0.016,
    -0.024,
    -0.031,
    -0.04,
    -0.049,
    -0.058,
    -0.067,
    -0.076,
    -0.085,
    -0.093,
    -0.101,
    -0.108,
    -0.114,
    -0.119,
    -0.122,
    -0.125,
    -0.126,
    -0.125,
    -0.122,
    -0.117,
    -0.11,
    -0.101,
    -0.089,
    -0.074,
    -0.057,
    -0.037,
    -0.013,
    0.013,
    0.043,
    0.077,
    0.114,
    0.154,
    0.197,
    0.243,
    0.291,
    0.342,
    0.394,
    0.448,
    0.503,
    0.558,
    0.613,
    0.668,
    0.722,
    0.775,
    0.825,
    0.873,
    0.917,
    0.958,
    0.993,
    1.023,
    1.047,
    1.063,
    1.072,
    1.073,
    1.066,
    1.053,
    1.034,
    1.008,
    0.977,
    0.94,
    0.899,
    0.854,
    0.805,
    0.753,
    0.698,
    0.641,
    0.582,
    0.523,
    0.463,
    0.403,
    0.344,
    0.286,
    0.23,
    0.177,
    0.127,
    0.081,
    0.038,
    -0.002,
    -0.039,
    -0.072,
    -0.101,
    -0.128,
    -0.15,
    -0.17,
    -0.186,
    -0.199,
    -0.208,
    -0.215,
    -0.219,
    -0.22,
    -0.219,
    -0.215,
    -0.209,
    -0.202,
    -0.193,
    -0.183,
    -0.172,
    -0.16,
    -0.148,
    -0.135,
    -0.122,
    -0.11,
    -0.097,
    -0.085,
    -0.073,
    -0.061,
    -0.05,
    -0.04,
    -0.03,
    -0.021,
    -0.012,
    -0.004,
    0.003,
    0.009,
    0.015,
    0.019,
    0.024,
    0.027,
    0.03,
    0.033,
    0.036,
    0.038,
    0.04,
    0.042,
    0.044,
    0.046,
    0.049,
    0.051,
    0.053,
    0.055,
    0.057,
    0.059,
    0.061,
    0.063,
    0.065,
    0.068,
    0.07,
    0.072,
    0.074,
    0.076,
    0.079,
    0.081,
    0.083,
    0.085,
    0.086,
    0.088,
    0.09,
    0.092,
    0.094,
    0.096,
    0.098,
    0.1,
    0.102,
    0.104,
    0.106,
    0.108,
    0.111,
    0.113,
    0.116,
    0.119,
    0.122,
    0.125,
    0.128,
    0.132,
    0.135,
    0.139,
    0.143,
    0.147,
    0.151,
    0.155,
    0.159,
    0.164,
    0.168,
    0.173,
    0.178,
    0.182,
    0.187,
    0.192,
    0.196,
    0.201,
    0.206,
    0.211,
    0.215,
    0.22,
    0.225,
    0.229,
    0.234,
    0.238,
    0.243,
    0.248,
    0.252,
    0.257,
    0.262,
    0.267,
    0.272,
    0.277,
    0.282,
    0.287,
    0.292,
    0.298,
    0.303,
    0.308,
    0.313,
    0.318,
    0.323,
    0.328,
    0.333,
    0.337,
    0.342,
    0.347,
    0.351,
    0.356,
    0.36,
    0.365,
    0.369,
    0.374,
    0.378,
    0.382,
    0.386,
    0.39,
    0.395,
    0.399,
    0.403,
    0.407,
    0.411,
    0.416,
    0.42,
    0.423,
    0.427,
    0.431,
    0.434,
    0.437,
    0.44,
    0.443,
    0.445,
    0.448,
    0.45,
    0.452,
    0.454,
    0.455,
    0.457,
    0.459,
    0.46,
    0.462,
    0.463,
    0.465,
    0.466,
    0.467,
    0.468,
    0.468,
    0.469,
    0.469,
    0.468,
    0.468,
    0.467,
    0.465,
    0.464,
    0.462,
    0.46,
    0.458,
    0.456,
    0.454,
    0.452,
    0.45,
    0.448,
    0.446,
    0.443,
    0.441,
    0.438,
    0.436,
    0.433,
    0.43,
    0.426,
    0.422,
    0.418,
    0.414,
    0.41,
    0.405,
    0.4,
    0.396,
    0.391,
    0.387,
    0.382,
    0.378,
    0.373,
    0.369,
    0.365,
    0.36,
    0.356,
    0.352,
    0.347,
    0.343,
    0.338,
    0.333,
    0.329,
    0.324,
    0.319,
    0.314,
    0.309,
    0.304,
    0.299,
    0.294,
    0.289,
    0.285,
    0.28,
    0.275,
    0.271,
    0.266,
    0.261,
    0.257,
    0.252,
    0.248,
    0.243,
    0.238,
    0.233,
    0.229,
    0.224,
    0.219,
    0.215,
    0.21,
    0.206,
    0.201,
    0.197,
    0.193,
    0.189,
    0.185,
    0.181,
    0.177,
    0.174,
    0.17,
    0.167,
    0.163,
    0.159,
    0.156,
    0.152,
    0.149,
    0.145,
    0.142,
    0.138,
    0.134,
    0.131,
    0.127,
    0.124,
    0.12,
    0.116,
    0.113,
    0.109,
    0.106,
    0.103,
    0.1,
    0.098,
    0.095,
    0.093,
    0.092,
    0.09,
    0.089,
    0.088,
    0.087,
    0.086,
    0.085,
    0.085,
    0.084,
    0.083,
    0.082,
    0.081,
    0.08,
    0.078,
    0.077,
    0.075,
    0.074,
    0.072,
    0.07,
    0.067,
    0.065,
    0.062,
    0.06,
    0.058,
    0.055,
    0.053,
    0.051,
    0.05,
    0.049,
    0.048,
    0.048,
    0.048,
    0.049,
    0.05,
    0.051,
    0.052,
    0.053,
    0.054,
    0.055,
    0.056,
    0.056,
    0.057,
    0.057,
    0.057,
    0.057,
    0.057,
    0.057,
    0.057,
    0.057,
    0.057,
    0.056,
    0.056,
    0.056,
    0.056,
    0.056,
    0.057,
    0.057,
    0.057,
    0.057,
    0.058,
    0.058,
    0.058,
    0.059,
    0.059,
    0.06,
    0.06,
    0.061,
    0.061,
    0.061,
    0.062,
    0.062,
    0.062,
    0.062,
    0.062,
    0.062,
    0.062,
    0.062,
    0.062,
    0.062,
    0.062,
    0.062,
    0.062,
    0.062,
    0.062,
    0.063,
    0.063,
    0.064,
    0.064,
    0.065,
    0.065,
    0.065,
    0.066,
    0.067,
    0.067,
    0.068,
    0.068,
    0.068,
    0.069,
    0.069,
    0.07,
    0.07,
    0.07,
    0.071,
    0.071,
    0.071,
    0.072,
    0.072,
    0.073,
    0.074,
    0.075,
    0.075,
    0.076,
    0.077,
    0.079,
    0.08,
    0.081,
    0.082
  ],
  "PPG": [
    0.792,
    0.745,
    0.712,
    0.697,
    0.696,
    0.698,
    0.697,
    0.691,
    0.683,
    0.672,
    0.66,
    0.646,
    0.631,
    0.614,
    0.595,
    0.576,
    0.555,
    0.533,
    0.51,
    0.486,
    0.462,
    0.437,
    0.412,
    0.387,
    0.361,
    0.335,
    0.31,
    0.284,
    0.259,
    0.234,
    0.21,
    0.187,
    0.164,
    0.142,
    0.121,
    0.102,
    0.083,
    0.066,
    0.051,
    0.037,
    0.025,
    0.015,
    0.007,
    0.001,
    0.029,
    0.114,
    0.242,
    0.403,
    0.583,
    0.771
  ],
  "Resp": [
    0.009,
    0.01,
    0.01,
    0.01,
    0.01,
    0.009,
    0.009,
    0.009,
    0.009,
    0.009,
    0.009,
    0.009,
    0.009,
    0.01,
    0.01,
    0.011,
    0.011,
    0.012,
    0.012,
    0.012,
    0.012,
    0.011,
    0.011,
    0.01,
    0.008,
    0.007,
    0.005,
    0.003,
    0.001,
    -0.001,
    -0.003,
    -0.005,
    -0.006,
    -0.008,
    -0.01,
    -0.012,
    -0.013,
    -0.016,
    -0.018,
    -0.021,
    -0.024,
    -0.027,
    -0.032,
    -0.036,
    -0.042,
    -0.047,
    -0.053,
    -0.059,
    -0.065,
    -0.072
  ],
  "Spo2": [
    98.871,
    101.921,
    97.619,
    99.008,
    94.976,
    100.138,
    96.902,
    99.158,
    97.833,
    97.134,
    96.043,
    97.63,
    97.122,
    97.179,
    98.876,
    97.795,
    96.561,
    94.584,
    94.727,
    98.369,
    95.756,
    97.862,
    95.873,
    96.453,
    99.297,
    101.096,
    97.749,
    99.38,
    99.917,
    102.756,
    100.455,
    97.355,
    100.193,
    95.734,
    98.771,
    103.034,
    95.356,
    98.014,
    99.919,
    101.476,
    95.076,
    96.369,
    100.362,
    100.714,
    101.056,
    96.515,
    95.243,
    96.123,
    98.22,
    99.044
  ],
  "temp": [
    38.94,
    36.561,
    35.657,
    36.382,
    38.944,
    37.153,
    36.108,
    35.725,
    36.979,
    37.683,
    38.257,
    38.818,
    38.894,
    36.974,
    37.713,
    36.228,
    37.548,
    39.28,
    36.929,
    35.174,
    39.145,
    37.206,
    36.813,
    38.207,
    37.162,
    37.93,
    38.483,
    37.823,
    39.217,
    36.773,
    35.631,
    37.636,
    37.028,
    37.167,
    36.119,
    37.091,
    38.958,
    37.747,
    36.38,
    38.986,
    39.746,
    35.494,
    36.81,
    36.784,
    37.538,
    38.029,
    35.114,
    35.537,
    36.767,
    37.9
  ],
  "SIS": [
    128.0,
    125.0,
    113.0,
    135.0,
    135.0,
    115.0,
    138.0,
    134.0,
    135.0,
    115.0,
    134.0,
    137.0,
    138.0,
    110.0,
    119.0,
    123.0,
    113.0,
    124.0,
    134.0,
    139.0,
    115.0,
    133.0,
    126.0,
    128.0,
    125.0,
    135.0,
    130.0,
    134.0,
    113.0,
    124.0,
    116.0,
    129.0,
    136.0,
    135.0,
    129.0,
    124.0,
    113.0,
    119.0,
    124.0,
    118.0,
    115.0,
    133.0,
    129.0,
    131.0,
    116.0,
    138.0,
    128.0,
    126.0,
    134.0,
    124.0
  ],
  "DIA": [
    78.0,
    72.0,
    85.0,
    74.0,
    79.0,
    86.0,
    87.0,
    81.0,
    71.0,
    71.0,
    83.0,
    81.0,
    89.0,
    80.0,
    83.0,
    71.0,
    86.0,
    79.0,
    75.0,
    84.0,
    86.0,
    89.0,
    75.0,
    87.0,
    77.0,
    85.0,
    77.0,
    88.0,
    75.0,
    86.0,
    86.0,
    79.0,
    77.0,
    83.0,
    86.0,
    77.0,
    86.0,
    78.0,
    84.0,
    73.0,
    81.0,
    72.0,
    84.0,
    71.0,
    70.0,
    84.0,
    75.0,
    84.0,
    81.0,
    78.0
  ]
}
