{
  "n lote": 216,
  "IDequipo": "E13",
  "fecha": "2024-07-6",
  "hora": "20:01:48",
  "elapsedtime": "108.0",
  "unidades": [
    "-",
    "-",
    "-",
    "Elapsed time = s",
    "ECG = mV",
    "PPG = a.u.",
    "Resp = L/min",
    "Spo2 = %",
    "temp = \u00b0C",
    "SIS = mmHg",
    "DIA = mmHg"
  ],
  "frecuencia": [
    "-",
    "-",
    "-",
    "-",
    "ECG = 1000 Hz",
    "PPG = 100 Hz",
    "Resp = 100 Hz",
    "spo2 = 100 Hz",
    "temp = 100 Hz",
    "SIS = 100 Hz",
    "DIA = 100 Hz"
  ],
  "ECG": [
    0.848,
    0.879,
    0.909,
    0.938,
    0.965,
    0.99,
    1.013,
    1.035,
    1.053,
    1.068,
    1.081,
    1.09,
    1.097,
    1.1,
    1.101,
    1.098,
    1.093,
    1.085,
    1.075,
    1.061,
    1.045,
    1.026,
    1.005,
    0.981,
    0.954,
    0.926,
    0.895,
    0.862,
    0.827,
    0.791,
    0.752,
    0.713,
    0.672,
    0.631,
    0.589,
    0.546,
    0.503,
    0.461,
    0.418,
    0.376,
    0.335,
    0.294,
    0.255,
    0.217,
    0.18,
    0.144,
    0.11,
    0.076,
    0.044,
    0.014,
    -0.015,
    -0.043,
    -0.069,
    -0.094,
    -0.116,
    -0.137,
    -0.157,
    -0.174,
    -0.19,
    -0.204,
    -0.216,
    -0.227,
    -0.237,
    -0.244,
    -0.251,
    -0.256,
    -0.26,
    -0.262,
    -0.263,
    -0.264,
    -0.263,
    -0.261,
    -0.258,
    -0.254,
    -0.249,
    -0.244,
    -0.238,
    -0.231,
    -0.224,
    -0.217,
    -0.209,
    -0.2,
    -0.192,
    -0.183,
    -0.174,
    -0.165,
    -0.157,
    -0.148,
    -0.139,
    -0.13,
    -0.122,
    -0.114,
    -0.106,
    -0.098,
    -0.091,
    -0.084,
    -0.077,
    -0.07,
    -0.064,
    -0.058,
    -0.053,
    -0.048,
    -0.043,
    -0.038,
    -0.034,
    -0.03,
    -0.026,
    -0.022,
    -0.019,
    -0.016,
    -0.013,
    -0.01,
    -0.008,
    -0.006,
    -0.004,
    -0.002,
    -0.001,
    0.001,
    0.001,
    0.001,
    0.001,
    0.001,
    0.001,
    0.001,
    0.001,
    0.001,
    0.001,
    0.002,
    0.002,
    0.002,
    0.003,
    0.003,
    0.003,
    0.004,
    0.004,
    0.005,
    0.005,
    0.006,
    0.006,
    0.006,
    0.007,
    0.007,
    0.007,
    0.008,
    0.008,
    0.008,
    0.008,
    0.008,
    0.009,
    0.009,
    0.009,
    0.009,
    0.01,
    0.01,
    0.01,
    0.01,
    0.011,
    0.011,
    0.012,
    0.012,
    0.012,
    0.013,
    0.013,
    0.014,
    0.014,
    0.014,
    0.015,
    0.015,
    0.016,
    0.016,
    0.016,
    0.017,
    0.017,
    0.018,
    0.018,
    0.019,
    0.019,
    0.02,
    0.02,
    0.021,
    0.021,
    0.022,
    0.023,
    0.023,
    0.024,
    0.025,
    0.026,
    0.026,
    0.027,
    0.028,
    0.029,
    0.029,
    0.03,
    0.031,
    0.031,
    0.032,
    0.033,
    0.033,
    0.034,
    0.034,
    0.035,
    0.036,
    0.036,
    0.037,
    0.038,
    0.039,
    0.04,
    0.041,
    0.042,
    0.043,
    0.044,
    0.046,
    0.047,
    0.048,
    0.049,
    0.05,
    0.051,
    0.053,
    0.054,
    0.055,
    0.056,
    0.058,
    0.059,
    0.061,
    0.063,
    0.065,
    0.067,
    0.069,
    0.071,
    0.073,
    0.075,
    0.077,
    0.079,
    0.081,
    0.082,
    0.083,
    0.084,
    0.086,
    0.087,
    0.087,
    0.089,
    0.09,
    0.091,
    0.092,
    0.094,
    0.096,
    0.098,
    0.1,
    0.103,
    0.106,
    0.109,
    0.112,
    0.115,
    0.119,
    0.122,
    0.126,
    0.13,
    0.134,
    0.138,
    0.142,
    0.145,
    0.149,
    0.152,
    0.155,
    0.157,
    0.159,
    0.161,
    0.162,
    0.164,
    0.165,
    0.167,
    0.168,
    0.17,
    0.172,
    0.174,
    0.177,
    0.179,
    0.183,
    0.186,
    0.189,
    0.193,
    0.197,
    0.2,
    0.204,
    0.208,
    0.212,
    0.215,
    0.219,
    0.223,
    0.226,
    0.23,
    0.233,
    0.237,
    0.24,
    0.244,
    0.247,
    0.25,
    0.254,
    0.257,
    0.261,
    0.264,
    0.268,
    0.272,
    0.275,
    0.279,
    0.283,
    0.287,
    0.291,
    0.294,
    0.298,
    0.302,
    0.306,
    0.309,
    0.313,
    0.316,
    0.319,
    0.322,
    0.325,
    0.328,
    0.331,
    0.334,
    0.336,
    0.339,
    0.341,
    0.343,
    0.345,
    0.348,
    0.35,
    0.352,
    0.354,
    0.357,
    0.359,
    0.362,
    0.365,
    0.368,
    0.372,
    0.375,
    0.379,
    0.383,
    0.386,
    0.39,
    0.393,
    0.397,
    0.4,
    0.402,
    0.404,
    0.406,
    0.408,
    0.409,
    0.411,
    0.412,
    0.413,
    0.415,
    0.416,
    0.418,
    0.419,
    0.421,
    0.423,
    0.425,
    0.427,
    0.429,
    0.43,
    0.432,
    0.433,
    0.434,
    0.435,
    0.435,
    0.435,
    0.435,
    0.435,
    0.435,
    0.435,
    0.435,
    0.435,
    0.436,
    0.436,
    0.436,
    0.437,
    0.437,
    0.438,
    0.438,
    0.438,
    0.438,
    0.438,
    0.438,
    0.438,
    0.438,
    0.437,
    0.436,
    0.435,
    0.434,
    0.433,
    0.432,
    0.43,
    0.429,
    0.427,
    0.426,
    0.424,
    0.422,
    0.42,
    0.418,
    0.416,
    0.414,
    0.412,
    0.41,
    0.408,
    0.405,
    0.403,
    0.4,
    0.398,
    0.395,
    0.393,
    0.39,
    0.388,
    0.385,
    0.383,
    0.38,
    0.377,
    0.375,
    0.372,
    0.369,
    0.366,
    0.363,
    0.36,
    0.358,
    0.354,
    0.351,
    0.348,
    0.345,
    0.342,
    0.339,
    0.335,
    0.332,
    0.329,
    0.326,
    0.323,
    0.32,
    0.317,
    0.313,
    0.31,
    0.307,
    0.304,
    0.3,
    0.296,
    0.293,
    0.289,
    0.285,
    0.281,
    0.277,
    0.273,
    0.268,
    0.264,
    0.26,
    0.256,
    0.252,
    0.248,
    0.244,
    0.24,
    0.236,
    0.233,
    0.229,
    0.226,
    0.223,
    0.219,
    0.217,
    0.214,
    0.211,
    0.208,
    0.205,
    0.203,
    0.2,
    0.196,
    0.193,
    0.189,
    0.185,
    0.18,
    0.176,
    0.171,
    0.166,
    0.16,
    0.155,
    0.151,
    0.146,
    0.142,
    0.138,
    0.134,
    0.131,
    0.128,
    0.126,
    0.123,
    0.121,
    0.119,
    0.117,
    0.115,
    0.113,
    0.111,
    0.109,
    0.107
  ],
  "PPG": [
    0.649,
    0.639,
    0.628,
    0.617,
    0.606,
    0.594,
    0.582,
    0.571,
    0.559,
    0.546,
    0.534,
    0.521,
    0.509,
    0.496,
    0.483,
    0.471,
    0.458,
    0.445,
    0.432,
    0.419,
    0.406,
    0.394,
    0.381,
    0.369,
    0.356,
    0.344,
    0.332,
    0.32,
    0.308,
    0.297,
    0.285,
    0.274,
    0.263,
    0.253,
    0.243,
    0.233,
    0.223,
    0.214,
    0.205,
    0.197,
    0.189,
    0.182,
    0.175,
    0.168,
    0.162,
    0.156,
    0.151,
    0.147,
    0.143,
    0.139
  ],
  "Resp": [
    0.365,
    0.358,
    0.35,
    0.342,
    0.334,
    0.326,
    0.318,
    0.311,
    0.303,
    0.295,
    0.288,
    0.28,
    0.272,
    0.264,
    0.256,
    0.248,
    0.239,
    0.23,
    0.221,
    0.212,
    0.203,
    0.194,
    0.185,
    0.177,
    0.168,
    0.16,
    0.152,
    0.145,
    0.137,
    0.13,
    0.124,
    0.117,
    0.111,
    0.105,
    0.099,
    0.093,
    0.088,
    0.082,
    0.076,
    0.07,
    0.065,
    0.06,
    0.055,
    0.05,
    0.045,
    0.041,
    0.037,
    0.033,
    0.029,
    0.026
  ],
  "Spo2": [
    96.59,
    98.597,
    95.286,
    95.004,
    95.878,
    99.702,
    98.508,
    96.905,
    99.652,
    99.595,
    97.878,
    98.035,
    99.011,
    98.084,
    95.282,
    98.498,
    98.093,
    97.105,
    97.51,
    97.238,
    99.26,
    98.005,
    99.771,
    97.622,
    95.081,
    100.203,
    97.992,
    95.61,
    97.954,
    96.427,
    100.471,
    96.132,
    97.245,
    96.761,
    97.699,
    97.605,
    96.119,
    100.184,
    97.495,
    97.01,
    97.719,
    96.414,
    95.311,
    97.853,
    98.519,
    95.178,
    100.09,
    99.347,
    94.737,
    99.698
  ],
  "temp": [
    36.575,
    35.77,
    35.889,
    36.955,
    35.401,
    35.084,
    38.685,
    36.057,
    35.029,
    35.509,
    35.797,
    37.503,
    37.285,
    40.977,
    36.584,
    35.353,
    36.84,
    38.04,
    34.267,
    36.745,
    36.786,
    37.651,
    38.566,
    36.006,
    35.008,
    34.982,
    37.697,
    38.684,
    35.039,
    37.018,
    38.256,
    38.351,
    34.769,
    35.38,
    34.755,
    38.48,
    36.989,
    36.318,
    35.636,
    35.924,
    38.932,
    38.023,
    36.765,
    37.059,
    35.133,
    33.986,
    37.521,
    35.683,
    38.284,
    36.935
  ],
  "SIS": [
    121.0,
    129.0,
    127.0,
    124.0,
    131.0,
    117.0,
    117.0,
    117.0,
    132.0,
    134.0,
    116.0,
    131.0,
    117.0,
    110.0,
    131.0,
    136.0,
    125.0,
    132.0,
    125.0,
    117.0,
    133.0,
    120.0,
    120.0,
    115.0,
    121.0,
    126.0,
    133.0,
    124.0,
    114.0,
    133.0,
    121.0,
    132.0,
    136.0,
    137.0,
    132.0,
    121.0,
    133.0,
    135.0,
    113.0,
    135.0,
    130.0,
    131.0,
    112.0,
    124.0,
    129.0,
    119.0,
    129.0,
    134.0,
    136.0,
    135.0
  ],
  "DIA": [
    88.0,
    86.0,
    84.0,
    79.0,
    77.0,
    88.0,
    88.0,
    88.0,
    72.0,
    79.0,
    89.0,
    78.0,
    70.0,
    87.0,
    78.0,
    76.0,
    88.0,
    87.0,
    81.0,
    71.0,
    70.0,
    88.0,
    70.0,
    71.0,
    87.0,
    75.0,
    78.0,
    86.0,
    83.0,
    79.0,
    74.0,
    72.0,
    79.0,
    77.0,
    70.0,
    86.0,
    78.0,
    82.0,
    75.0,
    77.0,
    84.0,
    87.0,
    83.0,
    87.0,
    82.0,
    72.0,
    86.0,
    81.0,
    82.0,
    87.0
  ]
}
