{
  "n lote": 437,
  "IDequipo": "E27",
  "fecha": "2024-07-22",
  "hora": "00:42:12",
  "elapsedtime": "218.499",
  "unidades": [
    "-",
    "-",
    "-",
    "Elapsed time = s",
    "ECG = mV",
    "PPG = a.u.",
    "Resp = L/min",
    "Spo2 = %",
    "temp = \u00b0C",
    "SIS = mmHg",
    "DIA = mmHg"
  ],
  "frecuencia": [
    "-",
    "-",
    "-",
    "-",
    "ECG = 1000 Hz",
    "PPG = 100 Hz",
    "Resp = 100 Hz",
    "spo2 = 100 Hz",
    "temp = 100 Hz",
    "SIS = 100 Hz",
    "DIA = 100 Hz"
  ],
  "ECG": [
    -0.071,
    -0.066,
    -0.061,
    -0.057,
    -0.053,
    -0.049,
    -0.045,
    -0.042,
    -0.039,
    -0.036,
    -0.033,
    -0.031,
    -0.028,
    -0.027,
    -0.025,
    -0.023,
    -0.022,
    -0.021,
    -0.02,
    -0.019,
    -0.018,
    -0.017,
    -0.017,
    -0.016,
    -0.015,
    -0.014,
    -0.013,
    -0.012,
    -0.011,
    -0.01,
    -0.009,
    -0.007,
    -0.006,
    -0.005,
    -0.003,
    -0.001,
    0.001,
    0.003,
    0.005,
    0.008,
    0.01,
    0.013,
    0.016,
    0.02,
    0.023,
    0.027,
    0.031,
    0.035,
    0.039,
    0.043,
    0.047,
    0.051,
    0.054,
    0.058,
    0.061,
    0.064,
    0.068,
    0.071,
    0.074,
    0.078,
    0.081,
    0.085,
    0.089,
    0.094,
    0.099,
    0.103,
    0.109,
    0.114,
    0.119,
    0.124,
    0.129,
    0.135,
    0.14,
    0.144,
    0.149,
    0.153,
    0.158,
    0.162,
    0.166,
    0.171,
    0.175,
    0.18,
    0.184,
    0.189,
    0.194,
    0.198,
    0.203,
    0.208,
    0.214,
    0.219,
    0.224,
    0.23,
    0.235,
    0.241,
    0.246,
    0.252,
    0.257,
    0.262,
    0.268,
    0.273,
    0.278,
    0.284,
    0.289,
    0.293,
    0.298,
    0.303,
    0.307,
    0.312,
    0.316,
    0.32,
    0.324,
    0.328,
    0.332,
    0.336,
    0.34,
    0.344,
    0.348,
    0.351,
    0.355,
    0.358,
    0.362,
    0.365,
    0.368,
    0.371,
    0.374,
    0.376,
    0.379,
    0.381,
    0.383,
    0.385,
    0.387,
    0.388,
    0.39,
    0.391,
    0.391,
    0.392,
    0.392,
    0.392,
    0.392,
    0.392,
    0.391,
    0.391,
    0.39,
    0.389,
    0.388,
    0.387,
    0.386,
    0.385,
    0.384,
    0.382,
    0.38,
    0.378,
    0.376,
    0.374,
    0.372,
    0.369,
    0.366,
    0.364,
    0.361,
    0.357,
    0.354,
    0.351,
    0.347,
    0.343,
    0.339,
    0.335,
    0.331,
    0.327,
    0.322,
    0.318,
    0.313,
    0.309,
    0.305,
    0.3,
    0.296,
    0.292,
    0.287,
    0.283,
    0.278,
    0.273,
    0.269,
    0.264,
    0.258,
    0.253,
    0.247,
    0.242,
    0.236,
    0.23,
    0.224,
    0.218,
    0.212,
    0.206,
    0.2,
    0.194,
    0.188,
    0.183,
    0.177,
    0.172,
    0.167,
    0.161,
    0.156,
    0.151,
    0.146,
    0.14,
    0.135,
    0.13,
    0.125,
    0.12,
    0.114,
    0.109,
    0.104,
    0.099,
    0.094,
    0.089,
    0.084,
    0.079,
    0.074,
    0.07,
    0.065,
    0.061,
    0.057,
    0.052,
    0.049,
    0.045,
    0.041,
    0.038,
    0.035,
    0.031,
    0.028,
    0.024,
    0.021,
    0.017,
    0.013,
    0.008,
    0.003,
    -0.001,
    -0.006,
    -0.011,
    -0.016,
    -0.02,
    -0.024,
    -0.028,
    -0.031,
    -0.034,
    -0.036,
    -0.038,
    -0.039,
    -0.04,
    -0.041,
    -0.042,
    -0.043,
    -0.043,
    -0.044,
    -0.045,
    -0.046,
    -0.047,
    -0.048,
    -0.049,
    -0.051,
    -0.052,
    -0.053,
    -0.055,
    -0.056,
    -0.058,
    -0.059,
    -0.061,
    -0.062,
    -0.063,
    -0.064,
    -0.065,
    -0.066,
    -0.067,
    -0.068,
    -0.068,
    -0.069,
    -0.069,
    -0.07,
    -0.07,
    -0.07,
    -0.071,
    -0.072,
    -0.072,
    -0.074,
    -0.075,
    -0.077,
    -0.078,
    -0.08,
    -0.082,
    -0.083,
    -0.085,
    -0.086,
    -0.087,
    -0.087,
    -0.087,
    -0.087,
    -0.086,
    -0.085,
    -0.084,
    -0.083,
    -0.082,
    -0.081,
    -0.08,
    -0.079,
    -0.079,
    -0.079,
    -0.079,
    -0.079,
    -0.079,
    -0.079,
    -0.08,
    -0.08,
    -0.08,
    -0.08,
    -0.08,
    -0.08,
    -0.08,
    -0.079,
    -0.079,
    -0.078,
    -0.078,
    -0.077,
    -0.077,
    -0.077,
    -0.077,
    -0.077,
    -0.077,
    -0.078,
    -0.078,
    -0.079,
    -0.079,
    -0.08,
    -0.08,
    -0.08,
    -0.08,
    -0.08,
    -0.08,
    -0.08,
    -0.08,
    -0.08,
    -0.079,
    -0.079,
    -0.079,
    -0.078,
    -0.078,
    -0.078,
    -0.077,
    -0.077,
    -0.077,
    -0.076,
    -0.076,
    -0.076,
    -0.075,
    -0.075,
    -0.075,
    -0.074,
    -0.074,
    -0.074,
    -0.074,
    -0.074,
    -0.074,
    -0.074,
    -0.074,
    -0.075,
    -0.075,
    -0.076,
    -0.077,
    -0.077,
    -0.078,
    -0.078,
    -0.079,
    -0.078,
    -0.078,
    -0.077,
    -0.076,
    -0.075,
    -0.073,
    -0.07,
    -0.068,
    -0.065,
    -0.063,
    -0.06,
    -0.058,
    -0.055,
    -0.053,
    -0.05,
    -0.048,
    -0.046,
    -0.044,
    -0.041,
    -0.039,
    -0.037,
    -0.034,
    -0.032,
    -0.029,
    -0.026,
    -0.023,
    -0.02,
    -0.017,
    -0.014,
    -0.01,
    -0.007,
    -0.003,
    0.001,
    0.004,
    0.008,
    0.012,
    0.016,
    0.021,
    0.025,
    0.03,
    0.035,
    0.04,
    0.045,
    0.05,
    0.056,
    0.062,
    0.068,
    0.074,
    0.08,
    0.086,
    0.091,
    0.097,
    0.102,
    0.107,
    0.111,
    0.116,
    0.12,
    0.124,
    0.128,
    0.132,
    0.136,
    0.14,
    0.145,
    0.149,
    0.153,
    0.158,
    0.162,
    0.167,
    0.171,
    0.175,
    0.178,
    0.181,
    0.184,
    0.187,
    0.189,
    0.19,
    0.191,
    0.192,
    0.193,
    0.194,
    0.194,
    0.194,
    0.194,
    0.194,
    0.194,
    0.194,
    0.194,
    0.193,
    0.193,
    0.192,
    0.19,
    0.189,
    0.187,
    0.184,
    0.181,
    0.178,
    0.174,
    0.171,
    0.167,
    0.162,
    0.158,
    0.154,
    0.149,
    0.144,
    0.14,
    0.135,
    0.131,
    0.126,
    0.121,
    0.116,
    0.111,
    0.105,
    0.1,
    0.094,
    0.088,
    0.082,
    0.075,
    0.069,
    0.063,
    0.057,
    0.051,
    0.045,
    0.039,
    0.033,
    0.028,
    0.023,
    0.018,
    0.013,
    0.009,
    0.004
  ],
  "PPG": [
    1.608,
    1.542,
    1.472,
    1.401,
    1.329,
    1.259,
    1.193,
    1.131,
    1.077,
    1.031,
    0.996,
    0.972,
    0.963,
    0.966,
    0.975,
    0.984,
    0.986,
    0.982,
    0.976,
    0.967,
    0.956,
    0.943,
    0.927,
    0.91,
    0.891,
    0.87,
    0.848,
    0.824,
    0.799,
    0.772,
    0.745,
    0.716,
    0.687,
    0.657,
    0.626,
    0.595,
    0.563,
    0.531,
    0.499,
    0.467,
    0.435,
    0.403,
    0.372,
    0.341,
    0.31,
    0.28,
    0.251,
    0.223,
    0.196,
    0.17
  ],
  "Resp": [
    -0.395,
    -0.4,
    -0.405,
    -0.409,
    -0.413,
    -0.417,
    -0.42,
    -0.423,
    -0.425,
    -0.428,
    -0.43,
    -0.432,
    -0.434,
    -0.436,
    -0.437,
    -0.439,
    -0.44,
    -0.441,
    -0.442,
    -0.442,
    -0.443,
    -0.443,
    -0.444,
    -0.444,
    -0.444,
    -0.444,
    -0.443,
    -0.443,
    -0.442,
    -0.441,
    -0.44,
    -0.439,
    -0.437,
    -0.436,
    -0.434,
    -0.432,
    -0.429,
    -0.427,
    -0.424,
    -0.421,
    -0.418,
    -0.415,
    -0.412,
    -0.408,
    -0.404,
    -0.401,
    -0.397,
    -0.392,
    -0.388,
    -0.383
  ],
  "Spo2": [
    98.003,
    98.149,
    99.375,
    96.858,
    98.507,
    99.122,
    95.726,
    97.599,
    102.445,
    100.293,
    93.802,
    99.348,
    101.774,
    99.003,
    97.105,
    99.313,
    100.506,
    92.8,
    95.819,
    98.133,
    100.064,
    98.757,
    98.037,
    99.335,
    99.708,
    95.726,
    95.964,
    97.197,
    100.084,
    96.57,
    99.516,
    98.296,
    98.427,
    96.872,
    99.093,
    101.508,
    100.884,
    97.629,
    97.243,
    99.644,
    96.787,
    98.841,
    98.383,
    99.457,
    97.187,
    96.676,
    95.865,
    98.064,
    95.465,
    100.977
  ],
  "temp": [
    38.518,
    36.303,
    36.135,
    35.474,
    37.976,
    35.498,
    34.45,
    38.588,
    36.685,
    33.455,
    36.542,
    37.421,
    38.792,
    39.403,
    36.564,
    36.387,
    35.122,
    37.816,
    39.247,
    38.577,
    36.885,
    37.52,
    36.699,
    37.417,
    40.245,
    36.486,
    37.299,
    37.473,
    37.503,
    41.924,
    35.5,
    34.014,
    37.073,
    38.005,
    33.688,
    37.898,
    37.198,
    33.573,
    35.879,
    37.713,
    35.703,
    35.477,
    36.756,
    41.073,
    35.927,
    36.815,
    33.381,
    38.267,
    37.89,
    35.434
  ],
  "SIS": [
    129.0,
    128.0,
    130.0,
    120.0,
    128.0,
    116.0,
    121.0,
    119.0,
    111.0,
    122.0,
    119.0,
    116.0,
    128.0,
    138.0,
    125.0,
    138.0,
    133.0,
    121.0,
    120.0,
    123.0,
    135.0,
    124.0,
    131.0,
    138.0,
    126.0,
    135.0,
    110.0,
    139.0,
    128.0,
    112.0,
    132.0,
    114.0,
    119.0,
    138.0,
    130.0,
    127.0,
    128.0,
    118.0,
    123.0,
    130.0,
    133.0,
    138.0,
    112.0,
    123.0,
    119.0,
    139.0,
    131.0,
    121.0,
    110.0,
    136.0
  ],
  "DIA": [
    70.0,
    89.0,
    88.0,
    83.0,
    83.0,
    77.0,
    77.0,
    88.0,
    84.0,
    84.0,
    88.0,
    78.0,
    80.0,
    87.0,
    72.0,
    85.0,
    76.0,
    79.0,
    82.0,
    84.0,
    77.0,
    86.0,
    83.0,
    76.0,
    84.0,
    87.0,
    73.0,
    81.0,
    82.0,
    73.0,
    72.0,
    73.0,
    86.0,
    79.0,
    86.0,
    83.0,
    86.0,
    79.0,
    76.0,
    88.0,
    81.0,
    88.0,
    86.0,
    80.0,
    77.0,
    78.0,
    76.0,
    71.0,
    85.0,
    77.0
  ]
}
