{
  "n lote": 235,
  "IDequipo": "N10",
  "fecha": "2024-07-22",
  "hora": "00:39:07",
  "elapsedtime": "117.500",
  "unidades": [
    "-",
    "-",
    "-",
    "Elapsed time = s",
    "ECG = mV",
    "PPG = a.u.",
    "Resp = L/min",
    "Spo2 = %",
    "temp = \u00b0C",
    "SIS = mmHg",
    "DIA = mmHg"
  ],
  "frecuencia": [
    "-",
    "-",
    "-",
    "-",
    "ECG = 1000 Hz",
    "PPG = 100 Hz",
    "Resp = 100 Hz",
    "spo2 = 100 Hz",
    "temp = 100 Hz",
    "SIS = 100 Hz",
    "DIA = 100 Hz"
  ],
  "ECG": [
    0.04,
    0.042,
    0.044,
    0.045,
    0.047,
    0.049,
    0.051,
    0.052,
    0.054,
    0.055,
    0.057,
    0.058,
    0.06,
    0.061,
    0.063,
    0.065,
    0.068,
    0.07,
    0.073,
    0.077,
    0.08,
    0.084,
    0.087,
    0.091,
    0.095,
    0.099,
    0.103,
    0.107,
    0.11,
    0.114,
    0.118,
    0.122,
    0.126,
    0.13,
    0.134,
    0.138,
    0.142,
    0.147,
    0.152,
    0.157,
    0.162,
    0.167,
    0.172,
    0.177,
    0.182,
    0.187,
    0.192,
    0.197,
    0.202,
    0.207,
    0.212,
    0.217,
    0.222,
    0.227,
    0.231,
    0.236,
    0.241,
    0.247,
    0.252,
    0.257,
    0.262,
    0.267,
    0.272,
    0.277,
    0.282,
    0.286,
    0.29,
    0.294,
    0.298,
    0.301,
    0.305,
    0.307,
    0.31,
    0.312,
    0.314,
    0.316,
    0.318,
    0.319,
    0.32,
    0.32,
    0.321,
    0.321,
    0.321,
    0.321,
    0.321,
    0.321,
    0.32,
    0.32,
    0.32,
    0.319,
    0.318,
    0.317,
    0.316,
    0.314,
    0.312,
    0.309,
    0.306,
    0.302,
    0.297,
    0.292,
    0.287,
    0.282,
    0.276,
    0.271,
    0.266,
    0.261,
    0.257,
    0.252,
    0.249,
    0.245,
    0.242,
    0.239,
    0.236,
    0.232,
    0.229,
    0.224,
    0.22,
    0.215,
    0.209,
    0.203,
    0.197,
    0.19,
    0.184,
    0.177,
    0.17,
    0.164,
    0.158,
    0.152,
    0.146,
    0.141,
    0.136,
    0.131,
    0.126,
    0.122,
    0.118,
    0.114,
    0.11,
    0.106,
    0.102,
    0.099,
    0.095,
    0.092,
    0.089,
    0.086,
    0.082,
    0.079,
    0.076,
    0.073,
    0.07,
    0.067,
    0.065,
    0.062,
    0.06,
    0.057,
    0.055,
    0.053,
    0.05,
    0.048,
    0.046,
    0.045,
    0.043,
    0.041,
    0.039,
    0.037,
    0.035,
    0.033,
    0.031,
    0.028,
    0.026,
    0.023,
    0.02,
    0.017,
    0.013,
    0.01,
    0.005,
    0.001,
    -0.004,
    -0.009,
    -0.015,
    -0.021,
    -0.028,
    -0.035,
    -0.043,
    -0.05,
    -0.058,
    -0.066,
    -0.074,
    -0.082,
    -0.09,
    -0.098,
    -0.105,
    -0.112,
    -0.119,
    -0.124,
    -0.129,
    -0.134,
    -0.137,
    -0.138,
    -0.139,
    -0.138,
    -0.135,
    -0.129,
    -0.122,
    -0.112,
    -0.099,
    -0.084,
    -0.066,
    -0.045,
    -0.021,
    0.007,
    0.038,
    0.072,
    0.11,
    0.151,
    0.195,
    0.241,
    0.291,
    0.343,
    0.396,
    0.452,
    0.509,
    0.567,
    0.625,
    0.683,
    0.741,
    0.797,
    0.852,
    0.904,
    0.953,
    0.998,
    1.039,
    1.074,
    1.104,
    1.129,
    1.148,
    1.16,
    1.167,
    1.167,
    1.161,
    1.148,
    1.13,
    1.105,
    1.074,
    1.037,
    0.995,
    0.948,
    0.896,
    0.841,
    0.781,
    0.72,
    0.656,
    0.592,
    0.528,
    0.465,
    0.403,
    0.343,
    0.285,
    0.229,
    0.175,
    0.124,
    0.076,
    0.031,
    -0.01,
    -0.049,
    -0.084,
    -0.117,
    -0.145,
    -0.171,
    -0.193,
    -0.213,
    -0.228,
    -0.241,
    -0.25,
    -0.257,
    -0.261,
    -0.262,
    -0.26,
    -0.256,
    -0.249,
    -0.241,
    -0.231,
    -0.22,
    -0.207,
    -0.194,
    -0.181,
    -0.167,
    -0.153,
    -0.139,
    -0.126,
    -0.113,
    -0.1,
    -0.088,
    -0.077,
    -0.066,
    -0.056,
    -0.047,
    -0.038,
    -0.03,
    -0.023,
    -0.016,
    -0.009,
    -0.004,
    0.001,
    0.006,
    0.01,
    0.014,
    0.018,
    0.021,
    0.023,
    0.026,
    0.028,
    0.03,
    0.032,
    0.033,
    0.035,
    0.036,
    0.037,
    0.037,
    0.038,
    0.039,
    0.039,
    0.04,
    0.04,
    0.041,
    0.041,
    0.042,
    0.042,
    0.043,
    0.044,
    0.045,
    0.047,
    0.048,
    0.05,
    0.052,
    0.054,
    0.056,
    0.058,
    0.061,
    0.064,
    0.067,
    0.069,
    0.072,
    0.075,
    0.078,
    0.081,
    0.083,
    0.086,
    0.088,
    0.09,
    0.092,
    0.094,
    0.096,
    0.098,
    0.1,
    0.102,
    0.105,
    0.107,
    0.11,
    0.113,
    0.117,
    0.12,
    0.124,
    0.128,
    0.132,
    0.136,
    0.14,
    0.144,
    0.148,
    0.152,
    0.156,
    0.16,
    0.164,
    0.168,
    0.172,
    0.176,
    0.18,
    0.183,
    0.187,
    0.191,
    0.194,
    0.198,
    0.202,
    0.206,
    0.21,
    0.215,
    0.219,
    0.224,
    0.229,
    0.235,
    0.24,
    0.246,
    0.252,
    0.258,
    0.264,
    0.27,
    0.275,
    0.281,
    0.287,
    0.292,
    0.297,
    0.303,
    0.308,
    0.313,
    0.317,
    0.322,
    0.326,
    0.331,
    0.335,
    0.339,
    0.343,
    0.348,
    0.352,
    0.356,
    0.36,
    0.365,
    0.37,
    0.375,
    0.38,
    0.386,
    0.391,
    0.397,
    0.403,
    0.409,
    0.414,
    0.42,
    0.425,
    0.43,
    0.435,
    0.439,
    0.443,
    0.446,
    0.449,
    0.452,
    0.455,
    0.458,
    0.46,
    0.462,
    0.464,
    0.465,
    0.467,
    0.468,
    0.469,
    0.47,
    0.471,
    0.472,
    0.473,
    0.474,
    0.475,
    0.476,
    0.477,
    0.478,
    0.479,
    0.479,
    0.48,
    0.48,
    0.481,
    0.481,
    0.481,
    0.48,
    0.48,
    0.479,
    0.478,
    0.477,
    0.475,
    0.474,
    0.472,
    0.47,
    0.467,
    0.465,
    0.462,
    0.459,
    0.456,
    0.452,
    0.449,
    0.446,
    0.442,
    0.438,
    0.435,
    0.431,
    0.428,
    0.424,
    0.42,
    0.417,
    0.413,
    0.409,
    0.405,
    0.401,
    0.397,
    0.393,
    0.389,
    0.384,
    0.38,
    0.375,
    0.371,
    0.366,
    0.361,
    0.357,
    0.352,
    0.347,
    0.341
  ],
  "PPG": [
    0.055,
    0.113,
    0.202,
    0.315,
    0.446,
    0.589,
    0.738,
    0.886,
    1.028,
    1.157,
    1.266,
    1.351,
    1.405,
    1.421,
    1.411,
    1.392,
    1.365,
    1.33,
    1.29,
    1.245,
    1.196,
    1.145,
    1.093,
    1.041,
    0.99,
    0.941,
    0.896,
    0.855,
    0.821,
    0.793,
    0.774,
    0.764,
    0.762,
    0.764,
    0.765,
    0.763,
    0.757,
    0.749,
    0.739,
    0.727,
    0.713,
    0.697,
    0.68,
    0.662,
    0.642,
    0.621,
    0.599,
    0.576,
    0.552,
    0.528
  ],
  "Resp": [
    0.009,
    0.01,
    0.01,
    0.011,
    0.011,
    0.013,
    0.014,
    0.015,
    0.017,
    0.02,
    0.022,
    0.025,
    0.027,
    0.03,
    0.033,
    0.036,
    0.04,
    0.043,
    0.046,
    0.05,
    0.053,
    0.057,
    0.062,
    0.066,
    0.071,
    0.077,
    0.083,
    0.09,
    0.097,
    0.105,
    0.112,
    0.121,
    0.129,
    0.137,
    0.145,
    0.154,
    0.161,
    0.169,
    0.176,
    0.183,
    0.191,
    0.198,
    0.205,
    0.212,
    0.219,
    0.227,
    0.235,
    0.243,
    0.252,
    0.261
  ],
  "Spo2": [
    100.692,
    96.705,
    98.395,
    98.539,
    98.707,
    95.61,
    95.881,
    97.723,
    95.131,
    99.367,
    100.933,
    98.941,
    99.693,
    97.743,
    98.98,
    99.67,
    98.186,
    97.814,
    99.244,
    100.96,
    99.115,
    98.119,
    96.204,
    99.964,
    99.249,
    99.271,
    101.869,
    97.341,
    95.766,
    96.367,
    97.115,
    102.387,
    96.944,
    97.146,
    101.49,
    99.619,
    97.546,
    99.231,
    99.243,
    97.91,
    101.498,
    99.068,
    98.32,
    96.293,
    93.683,
    95.568,
    97.908,
    96.0,
    98.906,
    95.05
  ],
  "temp": [
    34.329,
    36.766,
    36.981,
    34.561,
    34.939,
    39.841,
    34.338,
    37.539,
    37.866,
    35.899,
    36.112,
    35.623,
    36.631,
    38.878,
    35.362,
    40.166,
    38.733,
    34.074,
    36.724,
    34.917,
    35.747,
    35.771,
    35.122,
    34.59,
    35.894,
    35.527,
    39.064,
    38.299,
    37.477,
    36.612,
    35.59,
    36.762,
    38.452,
    36.721,
    36.276,
    38.452,
    38.944,
    39.089,
    40.053,
    37.067,
    37.705,
    36.264,
    36.221,
    36.23,
    38.138,
    36.363,
    37.013,
    35.953,
    35.958,
    38.794
  ],
  "SIS": [
    111.0,
    135.0,
    119.0,
    117.0,
    135.0,
    113.0,
    132.0,
    117.0,
    115.0,
    133.0,
    115.0,
    130.0,
    120.0,
    122.0,
    136.0,
    130.0,
    135.0,
    121.0,
    114.0,
    124.0,
    118.0,
    131.0,
    139.0,
    136.0,
    112.0,
    119.0,
    123.0,
    115.0,
    122.0,
    125.0,
    129.0,
    110.0,
    121.0,
    129.0,
    115.0,
    117.0,
    122.0,
    126.0,
    111.0,
    126.0,
    115.0,
    130.0,
    134.0,
    128.0,
    135.0,
    111.0,
    130.0,
    130.0,
    119.0,
    123.0
  ],
  "DIA": [
    84.0,
    71.0,
    73.0,
    70.0,
    70.0,
    86.0,
    72.0,
    84.0,
    86.0,
    89.0,
    70.0,
    82.0,
    75.0,
    83.0,
    89.0,
    86.0,
    86.0,
    75.0,
    79.0,
    76.0,
    70.0,
    79.0,
    84.0,
    85.0,
    80.0,
    84.0,
    73.0,
    70.0,
    78.0,
    81.0,
    89.0,
    72.0,
    86.0,
    78.0,
    73.0,
    74.0,
    75.0,
    75.0,
    72.0,
    77.0,
    89.0,
    87.0,
    70.0,
    75.0,
    86.0,
    76.0,
    81.0,
    86.0,
    75.0,
    87.0
  ]
}
